{
  "_class": "rectangle",
  "booleanOperation": -1,
  "clippingMaskMode": 0,
  "do_objectID": "F328D94C-E549-4BA5-A066-F16E98A282AA",
  "edited": false,
  "exportOptions": {
    "_class": "exportOptions",
    "do_objectID": "01560EC8-BBB1-4B00-B082-8AEC2B7F9494",
    "exportFormats": [
    ],
    "includedLayerIds": [
    ],
    "layerOptions": 0,
    "shouldTrim": false
  },
  "fixedRadius": 0,
  "frame": {
    "_class": "rect",
    "constrainProportions": false,
    "do_objectID": "7D76B65B-C3E2-44A1-B94F-8B73CAA670F7",
    "height": 61,
    "width": 154,
    "x": 0,
    "y": 184
  },
  "hasClippingMask": false,
  "hasConvertedToNewRoundCorners": true,
  "isClosed": true,
  "isFixedToViewport": false,
  "isFlippedHorizontal": false,
  "isFlippedVertical": false,
  "isLocked": false,
  "isVisible": true,
  "layerListExpandedType": 1,
  "name": "Rectangle Copy 3",
  "nameIsFixed": false,
  "pointRadiusBehaviour": 1,
  "points": [
    {
      "_class": "curvePoint",
      "cornerRadius": 0,
      "curveFrom": "{0, 0}",
      "curveMode": 1,
      "curveTo": "{0, 0}",
      "hasCurveFrom": false,
      "hasCurveTo": false,
      "point": "{0, 0}"
    },
    {
      "_class": "curvePoint",
      "cornerRadius": 0,
      "curveFrom": "{0.99999999999999811, 0}",
      "curveMode": 1,
      "curveTo": "{0.99999999999999811, 0}",
      "hasCurveFrom": false,
      "hasCurveTo": false,
      "point": "{0.99999999999999811, 0}"
    },
    {
      "_class": "curvePoint",
      "cornerRadius": 0,
      "curveFrom": "{0.99999999999999811, 1.0000000000000002}",
      "curveMode": 1,
      "curveTo": "{0.99999999999999811, 1.0000000000000002}",
      "hasCurveFrom": false,
      "hasCurveTo": false,
      "point": "{0.99999999999999811, 1.0000000000000002}"
    },
    {
      "_class": "curvePoint",
      "cornerRadius": 0,
      "curveFrom": "{0, 1.0000000000000002}",
      "curveMode": 1,
      "curveTo": "{0, 1.0000000000000002}",
      "hasCurveFrom": false,
      "hasCurveTo": false,
      "point": "{0, 1.0000000000000002}"
    }
  ],
  "resizingConstraint": 63,
  "resizingType": 0,
  "rotation": 0,
  "shouldBreakMaskChain": false,
  "style": {
    "_class": "style",
    "borders": [
      {
        "_class": "border",
        "color": {
          "_class": "color",
          "alpha": 1,
          "blue": 0.592,
          "green": 0.592,
          "red": 0.592
        },
        "fillType": 0,
        "isEnabled": false,
        "position": 1,
        "thickness": 1
      }
    ],
    "do_objectID": "4B81E066-219D-449E-931A-AC817638D1B9",
    "endMarkerType": 0,
    "fills": [
      {
        "_class": "fill",
        "color": {
          "_class": "color",
          "alpha": 1,
          "blue": 0,
          "green": 0,
          "red": 0
        },
        "fillType": 0,
        "isEnabled": true,
        "noiseIndex": 0,
        "noiseIntensity": 0,
        "patternFillType": 1,
        "patternTileScale": 1
      }
    ],
    "miterLimit": 10,
    "startMarkerType": 0,
    "windingRule": 1
  }
}